{"value0":{"values":[{"key":12,"value":12},{"key":11,"value":11},{"key":10,"value":3},{"key":9,"value":9},{"key":8,"value":8},{"key":7,"value":1},{"key":6,"value":6},{"key":5,"value":5},{"key":4,"value":4},{"key":3,"value":4},{"key":2,"value":2},{"key":1,"value":2},{"key":0,"value":2}],"regulators":[{"key":12,"value":1.0},{"key":11,"value":1.0},{"key":10,"value":1.0},{"key":9,"value":1.0},{"key":8,"value":1.0},{"key":7,"value":1.0},{"key":6,"value":1.0},{"key":5,"value":1.0},{"key":4,"value":1.0},{"key":3,"value":1.0},{"key":2,"value":1.0},{"key":1,"value":1.0},{"key":0,"value":1.0}],"tags":[{"key":12,"value":{"value0":{"value0":3654403871}}},{"key":11,"value":{"value0":{"value0":2241088705}}},{"key":10,"value":{"value0":{"value0":1967816791}}},{"key":9,"value":{"value0":{"value0":3223802825}}},{"key":8,"value":{"value0":{"value0":992123491}}},{"key":7,"value":{"value0":{"value0":3940076689}}},{"key":6,"value":{"value0":{"value0":1012192720}}},{"key":5,"value":{"value0":{"value0":503377730}}},{"key":4,"value":{"value0":{"value0":4081429421}}},{"key":3,"value":{"value0":{"value0":1319797088}}},{"key":2,"value":{"value0":{"value0":3869054794}}},{"key":1,"value":{"value0":{"value0":1064334982}}},{"key":0,"value":{"value0":{"value0":2453596643}}}],"uids":[0,1,2,3,4,5,6,7,8,9,10,11,12]}}